redipy/__init__.py
redipy/api.py
redipy/main.py
redipy/plugin.py
redipy/py.typed
redipy/script.py
redipy/util.py
redipy/backend/__init__.py
redipy/backend/backend.py
redipy/backend/runtime.py
redipy/graph/__init__.py
redipy/graph/cmd.py
redipy/graph/expr.py
redipy/graph/seq.py
redipy/helpers/__init__.py
redipy/helpers/cache.py
redipy/helpers/mavg.py
redipy/helpers/stack.py
redipy/memory/__init__.py
redipy/memory/gfun.py
redipy/memory/local.py
redipy/memory/rfun.py
redipy/memory/rt.py
redipy/memory/state.py
redipy/redis/__init__.py
redipy/redis/conn.py
redipy/redis/gpatch.py
redipy/redis/helpers.py
redipy/redis/lua.py
redipy/redis/rpatch.py
redipy/symbolic/__init__.py
redipy/symbolic/core.py
redipy/symbolic/expr.py
redipy/symbolic/fun.py
redipy/symbolic/rhash.py
redipy/symbolic/rlist.py
redipy/symbolic/rset.py
redipy/symbolic/rvar.py
redipy/symbolic/rzset.py
redipy/symbolic/seq.py
redipy-0.7.1.dist-info/LICENSE
redipy-0.7.1.dist-info/METADATA
redipy-0.7.1.dist-info/WHEEL
redipy-0.7.1.dist-info/top_level.txt
redipy-0.7.1.dist-info/RECORD
