Metadata-Version: 2.1
Name: redipy
Version: 0.7.1
Summary: redipy is a uniform interface to Redis-like storage systems. It allows you to use the same Redis API with different backends that implement the same functionality.
Author-email: Josua Krause <josua.krause@gmail.com>
License: Apache License
Project-URL: Source, https://github.com/JosuaKrause/redipy
Project-URL: Issues, https://github.com/JosuaKrause/redipy/issues
Project-URL: Changelog, https://github.com/JosuaKrause/redipy/blob/main/CHANGELOG.md
Keywords: redis,in-memory,uniform api
Classifier: Development Status :: 4 - Beta
Classifier: License :: OSI Approved :: Apache Software License
Classifier: Operating System :: OS Independent
Classifier: Programming Language :: Python :: 3
Classifier: Programming Language :: Python :: 3.11
Requires-Python: >=3.11
License-File: LICENSE
Requires-Dist: mypy >=1.10.0
Requires-Dist: pytz >=2023.3.post1
Requires-Dist: redis >=5.0.0
Requires-Dist: types-pytz >=2023.3.1.1
Requires-Dist: types-redis >=4.6.0.7
Provides-Extra: test
Requires-Dist: flake8-commas >=2.1.0 ; extra == 'test'
Requires-Dist: flake8-isort >=5.0.0 ; extra == 'test'
Requires-Dist: flake8 >=5.0.4 ; extra == 'test'
Requires-Dist: pre-commit >=3.4.0 ; extra == 'test'
Requires-Dist: pycodestyle >=2.9.1 ; extra == 'test'
Requires-Dist: pylint >=3.2.3 ; extra == 'test'
Requires-Dist: pytest-cov >=4.1.0 ; extra == 'test'
Requires-Dist: pytest >=7.4.2 ; extra == 'test'
